{
  "project_info": {
    "project_number": "451587929709",
    "project_id": "devfest-nantes-2022",
    "storage_bucket": "devfest-nantes-2022.firebasestorage.app"
  },
  "client": [
    {
      "client_info": {
        "mobilesdk_app_id": "1:451587929709:android:f722cda15cab1a04fe7164",
        "android_client_info": {
          "package_name": "com.gdgnantes.devfest.androidapp"
        }
      },
      "oauth_client": [],
      "api_key": [
        {
          "current_key": "AIzaSyAXLIC8Wa0mUn_jZ4Jauv2qFEPtob5yrGE"
        }
      ],
      "services": {
        "appinvite_service": {
          "other_platform_oauth_client": []
        }
      }
    },
    {
      "client_info": {
        "mobilesdk_app_id": "1:451587929709:android:51e8e56a23bccb93fe7164",
        "android_client_info": {
          "package_name": "com.gdgnantes.devfest.androidapp.dev"
        }
      },
      "oauth_client": [],
      "api_key": [
        {
          "current_key": "AIzaSyAXLIC8Wa0mUn_jZ4Jauv2qFEPtob5yrGE"
        }
      ],
      "services": {
        "appinvite_service": {
          "other_platform_oauth_client": []
        }
      }
    },
    {
      "client_info": {
        "mobilesdk_app_id": "1:451587929709:android:7d787bb23454ae27fe7164",
        "android_client_info": {
          "package_name": "com.gdgnantes.devfest.mobile.androidapp"
        }
      },
      "oauth_client": [],
      "api_key": [
        {
          "current_key": "AIzaSyAXLIC8Wa0mUn_jZ4Jauv2qFEPtob5yrGE"
        }
      ],
      "services": {
        "appinvite_service": {
          "other_platform_oauth_client": []
        }
      }
    },
    {
      "client_info": {
        "mobilesdk_app_id": "1:451587929709:android:f906593ddbe2da73fe7164",
        "android_client_info": {
          "package_name": "com.gdgnantes.devfest.mobile.androidapp.dev"
        }
      },
      "oauth_client": [],
      "api_key": [
        {
          "current_key": "AIzaSyAXLIC8Wa0mUn_jZ4Jauv2qFEPtob5yrGE"
        }
      ],
      "services": {
        "appinvite_service": {
          "other_platform_oauth_client": []
        }
      }
    }
  ],
  "configuration_version": "1"
}